izihawa_pdftools/__init__.py
izihawa_pdftools/cleaner.py
izihawa_pdftools/cleaner_cli.py
izihawa_pdftools/exceptions.py
izihawa_pdftools/text_collector.py
izihawa_pdftools/watermarks.py
izihawa_pdftools-1.0.20.dist-info/METADATA
izihawa_pdftools-1.0.20.dist-info/WHEEL
izihawa_pdftools-1.0.20.dist-info/RECORD
