Metadata-Version: 2.4
Name: izihawa-pdftools
Version: 1.0.20
Summary: Add your description here
Requires-Python: >=3.13
Requires-Dist: beautifulsoup4>=4.13.3
Requires-Dist: cryptography>=41.0.7
Requires-Dist: ebooklib>=0.18
Requires-Dist: izihawa-utils
Requires-Dist: pypdf>=5.4.0
